{
  "root": {
    "appLoadingText": "Запуск приложения",
    "linkCopied": "Ссылка скопирована",
    "title": "Codenames - кодовые имена",
    "cardsUpdated": "Карточки обновлены"
  },
  "lobby": {
    "sessionId": "ID сессии",
    "fieldSize": "Размер поля",
    "copyLink": "Копировать ссылку",
    "share": "Поделиться",
    "setUsername": "Ваш ник",
    "chooseTeam": "Выберите команду",
    "updateCards": "Обновить карточки",
    "startGame": "Погнали",
    "dictionary": "Словарь",
    "words": "Слов"
  },
  "game": {
    "leave": "Покинуть игру",
    "blueWin": "Победа синих",
    "redWin": "Победа красных"
  },
  "common": {
    "rotateDevice": "Пожалуйста, переверните устройство",
    "blueTeam": "Синяя команда",
    "redTeam": "Красная команда",
    "blues": "Синие",
    "reds": "Красные",
    "becomeCaptain": "Стать капитаном",
    "captain": "Капитан"
  },
  "error": {
    "linkNotCopied": "Ошибка. Не удалось скопировать ссылку",
    "cardsNotUpdated": "Ошибка. Не удалось обновить карточки",
    "common": "Произошла ошибка",
    "getDictionary": "Не удалось получить словарь"
  }
}
